{
  "3328163412": "¡Fuera en 360 segundos!",
  "2480962503": "¡Trabajo listo!",
  "490276034": "Procede a la extracción después de que el temporizador llegue a cero.",
  "3215974987": "Desmontador de bots",
  "254510718": "Sujétame el arma principal, que entro.",
  "74724350": "Completa el entrenamiento básico.",
  "854221043": "Procede a la extracción tras haber conseguido al menos 15 muestras raras entre todo el equipo en una misión.",
  "3625397401": "Completa una misión en dificultad extrema o superior sin que muera nadie.",
  "331887065": "Las muestras son las mejores amigas de un Helldiver",
  "1280579303": "Es la única forma de asegurarse…",
  "1328589529": "Ten 6 estratagemas de descarga orbital en el mismo lugar al mismo tiempo.",
  "279570205": "Obtén todos los trofeos de HELLDIVERS™ 2.",
  "1144600268": "¡Envíalo!",
  "2816087179": "Completa el objetivo táctico de un acechador en una colmena.",
  "2964567034": "Inicia una partida rápida",
  "1842016181": "Completa al menos 100 misiones.",
  "3959584611": "Joven bien parecido",
  "2049351693": "Lesiónate en todas las extremidades al mismo tiempo.",
  "3606813900": "Por los pelos",
  "240084251": "El poder de la democracia",
  "1266360816": "Vuélale a un bruto ambos brazos con disparos y luego procede a la extracción mientras siga vivo.",
  "2817236126": "Lo que no te mata…",
  "7350021": "El largo brazo de la justicia",
  "1476181576": "Completa una misión pero fracasa en la extracción.",
  "243360535": "Ayuda con la recarga a un compañero de equipo.",
  "2877533264": "Nada es más grande que la libertad",
  "2943934930": "Patriota",
  "3377781636": "Completa una misión con dificultad difícil o superior sin que nadie dispare su arma principal o de apoyo.",
  "3383073796": "Devuelve una granada activada.",
  "1841056965": "¡Tomad esto!",
  "3552395834": "Mata a 5 000 enemigos.",
  "3679744062": "¡Cómete esta!",
  "3167134455": "Juega a una misión de defensa planetaria.",
  "2474948923": "La democracia aún no ha acabado contigo",
  "2771110748": "Inicia una partida rápida solo con amigos",
  "1478360991": "Alcanza el máximo nivel en un módulo de la nave.",
  "2764315601": "Salto en picado",
  "1071140672": "Extrayendo por el campo",
  "2664916455": "Partida rápida con amigos",
  "1488816523": "Los tíos guais no miran a las explo… ¡AAAAH!",
  "911872437": "Paquete de 150 Créditos de Supertierra",
  "2538735225": "Mata a un cargador con una cápsula de reabastecimiento.",
  "3045882396": "Mata a 150 enemigos en una sola misión.",
  "2311231392": "Superciudadano",
  "3508298212": "Procede a la extracción en una misión durante la noche.",
  "2570980737": "El epítome de Supertierra",
  "3086803146": "Juega a una misión de bots.",
  "472312330": "La ciencia se hace por cantidad",
  "788445221": "Paquete de 2100 (1500 + 600 adicionales) Créditos de Supertierra",
  "3525879475": "¡Por el bien mayor!",
  "1256112630": "Partida rápida",
  "1031312853": "¡Suministros sorpresa!",
  "2692147882": "Mejora todos los módulos de la nave al menos un nivel.",
  "2599416825": "Juega al menos a 50 misiones.",
  "1332152835": "Por algo le dicen táctico",
  "2502670206": "Promotor de sinergias",
  "2715791332": "Completa 10 objetivos tácticos.",
  "3884685493": "Completa una misión de bombardeo con dificultad extrema y procede a la extracción en menos de 6 minutos.",
  "1538898674": "Derrota a un titán de bilis.",
  "1427976274": "Juega a una misión de bichos.",
  "3164004999": "Mata a 25 enemigos con una sola estratagema.",
  "3385453702": "Sin trampa ni cartón",
  "752968066": "Paquete de 1000 (750 + 250 adicionales) Créditos de Supertierra",
  "2346618264": "Dispara al menos 150 balas de una sola vez y mata al menos a 10 enemigos.",
  "1954310570": "¡Que no queden ni las cenizas!",
  "2367885192": "Procede a la extracción con un escuadrón completo en una misión con dificultad difícil o superior.",
  "3982625721": "Derrota a un bruto.",
  "552362711": "Procede a la extracción tras haber conseguido al menos 15 muestras comunes.",
  "3175499143": "Suelen llegar de noche…",
  "1741663299": "¡Patata caliente!",
  "3690650666": "Mata a un objetivo desde una distancia superior a los 100 metros.",
  "1495807816": "El acoso es ilegal",
  "2700797469": "Haz tu parte",
  "3143868727": "¡Extractamente!",
  "1956109868": "Extendiendo la democracia gestionada",
  "1456717076": "Paquete de 375 Créditos de Supertierra",
  "235196461": "Mata a 100 enemigos con daño por fuego en una sola misión.",
  "2537357154": "Golpéate hasta quedar como una muñeca de trapo mientras usas la mochila de salto.",
  "3655668821": "Vuela al menos 25 metros con la onda expansiva de una explosión.",
  "4011519829": "Mata a un bicho guerrero con una escopeta desde un metro de distancia o menos.",
  "421687485": "Completamente operativo",
  "1104401796": "Dejémoslo en empate",
  "2258743961": "Aplastador de bichos",
  "2932688770": "¡Sujétame el cubalibre!",
  "1647024014": "Cura a otro jugador con estims.",
  "442059879": "Personaliza a tu Helldiver con una capa, una armadura y un casco nuevos.",
  "921854660": "Cuanto más grandes…"
}