{
  "1864299915": "Mandato #TERM",
  "3075853207": "POLÍTICA:",
  "3669227538": "AGUARDA",
  "709049035": "CANDIDATO NÃO ELEGÍVEL PARA VOTOS",
  "3161593322": "VOTO FALHADO",
  "157403948": "VOTO BEM-SUCEDIDO",
  "432275452": "Cumpriste o teu dever democrático\nMUITO BEM!",
  "1647647552": "Aguarda enquanto a Super Terra processa democraticamente o teu voto.",
  "35708001": "Votar",
  "918788164": "BIOGRAFIA:",
  "2565771413": "A ELEIÇÃO TERMINA EM: ",
  "4275589329": "#DAYS DIAS #HOURS HORAS #MINUTES MIN",
  "3800224967": "MANDATO #TERM",
  "2098644286": "A ELEIÇÃO COMEÇA EM: ",
  "437129953": "#DAYS DIAS #HOURS HORAS #MINUTES MIN"
}