{
  "1332152835": "Es kommt alles auf die Taktik an",
  "2367885192": "Evakuiere bei einer Mission auf der Schwierigkeit Schwer oder höher mit einem vollständigen Trupp.",
  "3175499143": "Sie kommen meistens nachts heraus ...",
  "2771110748": "Starte eine „Schnelles Spiel“-Sitzung nur mit Freunden.",
  "3625397401": "Schließe eine Mission auf der Schwierigkeit Extrem oder höher ab, ohne dass jemand stirbt.",
  "854221043": "Evakuiere als Team mit mindestens 15 seltenen Proben aus einer Mission.",
  "2502670206": "Synergien fördern",
  "2664916455": "Schnelles Spiel mit Freunden",
  "4011519829": "Erledige einen Bug-Krieger aus 1 Meter Entfernung mit einer Schrotflinte.",
  "279570205": "Sammle alle Trophäen in HELLDIVERS™ 2.",
  "1488816523": "Coole Leute schauen nicht auf – AHHH!",
  "243360535": "Biete einem Teammitglied Nachladeunterstützung.",
  "752968066": "Paket mit 1.000 (750 + 250 als Bonus) Über-Credits",
  "2049351693": "Erleide Verletzungen an allen Gliedmaßen gleichzeitig.",
  "2480962503": "Job erledigt!",
  "3383073796": "Wirf eine scharfe Granate zurück.",
  "3655668821": "Lass dich von der Schockwelle einer Explosion mindestens 25 Meter katapultieren.",
  "2692147882": "Schalte mindestens eine Verbesserung in jedem Schiffsmodul frei.",
  "1144600268": "Verschifft",
  "1266360816": "Schieße einem Hulk beide Arme ab und evakuiere, während er noch lebt.",
  "74724350": "Schließe das Basistraining ab.",
  "1476181576": "Schließe eine Mission ab, ohne zu evakuieren.",
  "552362711": "Evakuiere mit mindestens 15 gewöhnlichen Proben.",
  "1104401796": "Einigen wir uns auf unentschieden",
  "472312330": "Wissenschaft erfordert Quantität",
  "1956109868": "Verbreitung der gelenkten Demokratie",
  "3045882396": "Erledige im Laufe einer Mission 150 Feinde.",
  "3164004999": "Erledige 25 Feinde mit einer Taktikausrüstung.",
  "3525879475": "Für die gute Sache!",
  "2700797469": "Deinen Teil machen",
  "1031312853": "Vom Vorräter erwischt!",
  "235196461": "Erledige im Laufe einer Mission 100 Feinde mit Feuerschaden.",
  "2538735225": "Erledige einen Stürmer mit einem Nachschub-Pod.",
  "1071140672": "Evakuierung auf dem Land",
  "2474948923": "Die Demokratie ist noch nicht fertig mit dir",
  "3508298212": "Evakuiere aus einer Mission bei Nacht.",
  "1841056965": "Nimm das!",
  "921854660": "Je größer sie sind ...",
  "2311231392": "Über-Bürger",
  "2537357154": "Bring dich mit einem Sprungpaket in einen unkontrollierten Ragdoll-Zustand.",
  "1280579303": "Nur so kann man sicher sein ...",
  "2964567034": "Starte eine „Schnelles Spiel“-Sitzung.",
  "2816087179": "Schließe ein Pirscher-Versteck-Taktikziel ab.",
  "1456717076": "Paket mit 375 Über-Credits",
  "3086803146": "Spiele 1 Bot-Mission.",
  "3328163412": "Nur noch 360 Sekunden!",
  "3606813900": "Gerade rechtzeitig",
  "2817236126": "Was uns nicht umbringt ...",
  "3679744062": "Friss das!",
  "331887065": "Es geht doch nichts über Proben",
  "1427976274": "Spiele 1 Bug-Mission.",
  "1842016181": "Schließe mindestens 100 Missionen ab.",
  "1647024014": "Heile einen anderen Spieler mit Spritzen.",
  "490276034": "Evakuiere, nachdem der Timer bei null angekommen ist.",
  "7350021": "Der lange Arm der Gerechtigkeit",
  "1478360991": "Schalte alle Verbesserungen in einem Schiffsmodul frei.",
  "2346618264": "Feuere mindestens 150 Mal in einer Salve ab und erledige mindestens 10 Feinde.",
  "3690650666": "Erledige ein Ziel aus über 100 Metern Entfernung.",
  "3959584611": "Stattlicher Bursche",
  "3884685493": "Schließe eine vollständige Blitzmission auf der Schwierigkeit Extrem ab und evakuiere in unter 6 Minuten.",
  "911872437": "Paket mit 150 Über-Credits",
  "2943934930": "Patriot",
  "3143868727": "Reibungslose Evakuierung",
  "2599416825": "Spiele mindestens 50 Missionen.",
  "1741663299": "Heiße Kartoffel!",
  "1495807816": "Stalking ist illegal",
  "3215974987": "Bot-Verschrotter",
  "3982625721": "Besiege einen Hulk.",
  "1954310570": "Tod durch Feuer",
  "1328589529": "Platziere 6 Orbitalsperrfeuer-Taktikausrüstungen zur gleichen Zeit am gleichen Ort.",
  "442059879": "Individualisiere deinen Helldiver mit einem neuen Umhang, einer Panzerung und einem Helm.",
  "2258743961": "Bug-Zerstampfer",
  "2877533264": "Nichts ist größer als Freiheit",
  "3377781636": "Schließe eine Mission auf der Schwierigkeit Schwer oder höher ab, ohne dass jemand seine Primär- oder Unterstützungswaffe abfeuert.",
  "2764315601": "Helldiver",
  "3385453702": "Das einzig Wahre",
  "2932688770": "Halt mal kurz meine Freiheit!",
  "240084251": "Die Macht der Demokratie",
  "1538898674": "Besiege einen Säuretitan.",
  "421687485": "Voll einsatzfähig",
  "3167134455": "Spiele eine planetare Verteidigungsmission.",
  "3552395834": "Erledige 5.000 Feinde.",
  "2715791332": "Schließe 10 Taktikziele ab.",
  "254510718": "Pass auf meine Primärwaffe auf, ich gehe rein!",
  "1256112630": "Schnelles Spiel",
  "788445221": "Paket mit 2.100 (1.500 + 600 als Bonus) Über-Credits",
  "2570980737": "Die Verkörperung von Über-Erde"
}